setup.py
cwthon/__init__.py
cwthon/_base.py
cwthon/_err.py
cwthon/_util.py
cwthon/chatwork.py
cwthon/chatwork_prop.py
cwthon.egg-info/PKG-INFO
cwthon.egg-info/SOURCES.txt
cwthon.egg-info/dependency_links.txt
cwthon.egg-info/requires.txt
cwthon.egg-info/top_level.txt
tests/__init__.py
tests/cwthonTest.py