Metadata-Version: 1.1
Name: cwthon
Version: 0.1.3.2
Summary: A Python wrapper of KDDI's ChatWork API
Home-page: https://github.com/ginyolith/cwthon
Author: ginyolith
Author-email: ginolith@gmail.com
License: MIT
Keywords: chatwork api wrapper
Platform: UNKNOWN
Classifier: Development Status :: 3 - Alpha
Classifier: License :: OSI Approved :: MIT License
Classifier: Programming Language :: Python :: 3.5
